CHANGES.txt
COPYRIGHT.txt
LICENSE.txt
README.txt
bootstrap.py
buildout.cfg
setup.py
src/z3c/__init__.py
src/z3c.rmldocument.egg-info/PKG-INFO
src/z3c.rmldocument.egg-info/SOURCES.txt
src/z3c.rmldocument.egg-info/dependency_links.txt
src/z3c.rmldocument.egg-info/namespace_packages.txt
src/z3c.rmldocument.egg-info/not-zip-safe
src/z3c.rmldocument.egg-info/requires.txt
src/z3c.rmldocument.egg-info/top_level.txt
src/z3c/rmldocument/README.txt
src/z3c/rmldocument/TODO.txt
src/z3c/rmldocument/__init__.py
src/z3c/rmldocument/document.py
src/z3c/rmldocument/interfaces.py
src/z3c/rmldocument/tests.py
src/z3c/rmldocument/examples/example1.rml